plantumlcli/__init__.py
plantumlcli/__main__.py
plantumlcli/config/__init__.py
plantumlcli/config/meta.py
plantumlcli/download/__init__.py
plantumlcli/download/base.py
plantumlcli/download/exist_versions.py
plantumlcli/entry/__init__.py
plantumlcli/entry/base.py
plantumlcli/entry/cli.py
plantumlcli/entry/general.py
plantumlcli/entry/local.py
plantumlcli/entry/remote.py
plantumlcli/models/__init__.py
plantumlcli/models/base.py
plantumlcli/models/local.py
plantumlcli/models/remote.py
plantumlcli/utils/__init__.py
plantumlcli/utils/concurrent.py
plantumlcli/utils/decorator.py
plantumlcli/utils/download.py
plantumlcli/utils/encoding.py
plantumlcli/utils/execute.py
plantumlcli/utils/file.py
plantumlcli/utils/function.py
plantumlcli/utils/session.py
plantumlcli-0.2.0.dist-info/LICENSE
plantumlcli-0.2.0.dist-info/METADATA
plantumlcli-0.2.0.dist-info/WHEEL
plantumlcli-0.2.0.dist-info/entry_points.txt
plantumlcli-0.2.0.dist-info/top_level.txt
plantumlcli-0.2.0.dist-info/RECORD
