Metadata-Version: 2.1
Name: plantumlcli
Version: 0.2.0
Summary: An easy-to-use plantuml cli for everyone.
Home-page: https://github.com/HansBug/plantumlcli
Author: HansBug
Author-email: hansbug@buaa.edu.cn
License: Apache License, Version 2.0
Project-URL: Documentation, https://github.com/HansBug/plantumlcli/blob/main/README.md
Project-URL: Source, https://github.com/HansBug/plantumlcli
Project-URL: Issue tracker, https://github.com/HansBug/plantumlcli/issues
Keywords: python,plantuml,diagrams
Classifier: Development Status :: 5 - Production/Stable
Classifier: Intended Audience :: Developers
Classifier: License :: OSI Approved :: Apache Software License
Classifier: Programming Language :: Python
Classifier: Programming Language :: Python :: 3
Classifier: Programming Language :: Python :: 3.7
Classifier: Programming Language :: Python :: 3.8
Classifier: Programming Language :: Python :: 3.9
Classifier: Programming Language :: Python :: 3.10
Classifier: Programming Language :: Python :: 3.11
Classifier: Programming Language :: Python :: Implementation :: PyPy
Requires-Python: >=3.7
License-File: LICENSE
Requires-Dist: click >=7.0
Requires-Dist: colorama >=0.4
Requires-Dist: requests >=2.12
Requires-Dist: urlobject >=2.4
Requires-Dist: pyquery >=1.4
Requires-Dist: prettytable >=1.0
Requires-Dist: chardet >=3.0
Requires-Dist: hbutils >=0.9.0
Requires-Dist: random-user-agent
Requires-Dist: natsort
Requires-Dist: tqdm
Provides-Extra: dev
Requires-Dist: ruff ; extra == 'dev'
Requires-Dist: tqdm ; extra == 'dev'
Requires-Dist: natsort ; extra == 'dev'
Provides-Extra: doc
Requires-Dist: sphinx >=3.2.0 ; extra == 'doc'
Requires-Dist: Jinja2 ~=3.0.0 ; extra == 'doc'
Requires-Dist: sphinx-rtd-theme >=0.4.3 ; extra == 'doc'
Requires-Dist: enum-tools ~=0.9.0 ; extra == 'doc'
Requires-Dist: sphinx-toolbox ; extra == 'doc'
Requires-Dist: packaging ; extra == 'doc'
Requires-Dist: sphinx-multiversion >=0.2.4 ; extra == 'doc'
Requires-Dist: where ~=1.0.2 ; extra == 'doc'
Requires-Dist: easydict <2,>=1.7 ; extra == 'doc'
Provides-Extra: lint
Requires-Dist: flake8 >=5.0.0 ; extra == 'lint'
Provides-Extra: pdf
Requires-Dist: cairosvg >=2.6.0 ; extra == 'pdf'
Provides-Extra: test
Requires-Dist: pytest ~=6.2.5 ; extra == 'test'
Requires-Dist: pytest-cov ~=3.0.0 ; extra == 'test'
Requires-Dist: pytest-mock ~=3.6.1 ; extra == 'test'
Requires-Dist: pytest-xdist >=1.34.0 ; extra == 'test'
Requires-Dist: pytest-rerunfailures ~=10.2 ; extra == 'test'
Requires-Dist: pytest-timeout ~=2.0.2 ; extra == 'test'
Requires-Dist: pytest-benchmark ~=3.4.0 ; extra == 'test'
Requires-Dist: more-itertools <8,>=7 ; extra == 'test'
Requires-Dist: testtools >=2 ; extra == 'test'
Requires-Dist: coverage >=5 ; extra == 'test'
Requires-Dist: mock >=4.0.3 ; extra == 'test'
Requires-Dist: huggingface-hub ; extra == 'test'
Requires-Dist: pysyslimit >=0.5.0 ; extra == 'test'
Requires-Dist: flake8 ~=3.5 ; extra == 'test'
Requires-Dist: easydict <2,>=1.7 ; extra == 'test'
Requires-Dist: where >=1.0.2 ; extra == 'test'
Requires-Dist: cairosvg >=2.6.0 ; (python_version > "3.8") and extra == 'test'
